testplan/__init__.py
testplan/base.py
testplan/defaults.py
testplan/environment.py
testplan/parser.py
testplan/version.py
testplan/cli/__init__.py
testplan/cli/display.py
testplan/cli/tpsreport.py
testplan/cli/commands/__init__.py
testplan/cli/commands/readers.py
testplan/cli/commands/writers.py
testplan/cli/converter/__init__.py
testplan/cli/merger/__init__.py
testplan/cli/merger/mergers.py
testplan/cli/utils/__init__.py
testplan/cli/utils/actions.py
testplan/cli/utils/command_list.py
testplan/common/__init__.py
testplan/common/config/__init__.py
testplan/common/config/base.py
testplan/common/entity/__init__.py
testplan/common/entity/base.py
testplan/common/exporters/__init__.py
testplan/common/exporters/constants.py
testplan/common/exporters/pdf.py
testplan/common/remote/__init__.py
testplan/common/remote/remote_driver.py
testplan/common/remote/remote_resource.py
testplan/common/remote/remote_service.py
testplan/common/report/__init__.py
testplan/common/report/base.py
testplan/common/report/log.py
testplan/common/report/schemas.py
testplan/common/serialization/__init__.py
testplan/common/serialization/base.py
testplan/common/serialization/fields.py
testplan/common/serialization/schemas.py
testplan/common/utils/__init__.py
testplan/common/utils/callable.py
testplan/common/utils/comparison.py
testplan/common/utils/composer.py
testplan/common/utils/context.py
testplan/common/utils/convert.py
testplan/common/utils/difflib.py
testplan/common/utils/documentation_helper.py
testplan/common/utils/exceptions.py
testplan/common/utils/graph.py
testplan/common/utils/helper.py
testplan/common/utils/interface.py
testplan/common/utils/json.py
testplan/common/utils/logfile.py
testplan/common/utils/logger.py
testplan/common/utils/match.py
testplan/common/utils/networking.py
testplan/common/utils/package.py
testplan/common/utils/parser.py
testplan/common/utils/path.py
testplan/common/utils/process.py
testplan/common/utils/registry.py
testplan/common/utils/remote.py
testplan-25.8.0.dist-info/licenses/LICENSE.md
testplan-25.8.0.dist-info/licenses/NOTICE.rst
testplan-25.8.0.dist-info/METADATA
testplan-25.8.0.dist-info/WHEEL
testplan-25.8.0.dist-info/entry_points.txt
testplan-25.8.0.dist-info/top_level.txt
testplan-25.8.0.dist-info/RECORD
