Metadata-Version: 2.4
Name: testplan
Version: 25.8.0
Summary: Testplan testing framework
Author-email: Morgan Stanley <eti-testplan@morganstanley.com>
License:                                  Apache License
Project-URL: homepage, https://github.com/morganstanley/testplan
Project-URL: documentation, https://testplan.readthedocs.io
Keywords: testplan,test,unittest,integrationtest
Classifier: Development Status :: 5 - Production/Stable
Classifier: Intended Audience :: Developers
Classifier: License :: OSI Approved :: Apache Software License
Classifier: Programming Language :: Python :: 3
Classifier: Programming Language :: Python :: 3.9
Classifier: Programming Language :: Python :: 3.10
Classifier: Programming Language :: Python :: 3.11
Classifier: Programming Language :: Python :: 3.12
Classifier: Topic :: Software Development :: Testing
Classifier: Topic :: Software Development :: Testing :: Unit
Requires-Python: >=3.9
License-File: LICENSE.md
License-File: NOTICE.rst
Requires-Dist: setuptools
Requires-Dist: pytest
Requires-Dist: psutil
Requires-Dist: schema
Requires-Dist: tzlocal
Requires-Dist: lxml
Requires-Dist: reportlab
Requires-Dist: marshmallow<4.0.0
Requires-Dist: termcolor
Requires-Dist: colorama
Requires-Dist: pyzmq
Requires-Dist: terminaltables
Requires-Dist: requests>=2.31.0
Requires-Dist: boltons
Requires-Dist: validators<=0.20.0
Requires-Dist: Pillow
Requires-Dist: rpyc
Requires-Dist: matplotlib
Requires-Dist: coverage
Requires-Dist: typing_extensions
Requires-Dist: dill
Requires-Dist: parse
Requires-Dist: paramiko[all]
Requires-Dist: orjson
Requires-Dist: exceptiongroup>=1.2.2; python_full_version < "3.11"
Requires-Dist: jinja2>=3.1.6
Requires-Dist: click>=8.1.8
Requires-Dist: gherkin-official>=32.1.2
Provides-Extra: interactive
Requires-Dist: flask>=2.2.5; extra == "interactive"
Requires-Dist: werkzeug>=2.2.3; extra == "interactive"
Requires-Dist: flask-restx>=1.1.0; extra == "interactive"
Requires-Dist: cheroot>=10.0.1; extra == "interactive"
Requires-Dist: flask-orjson>=2.0.0; extra == "interactive"
Provides-Extra: plotly
Requires-Dist: pandas>=2.2.3; extra == "plotly"
Requires-Dist: plotly>=6.1.0; extra == "plotly"
Provides-Extra: all
Requires-Dist: testplan[interactive,plotly]; extra == "all"
Dynamic: license-file
